shiny_tail/__init__.py
shiny_tail/tailwind.py
shiny_tail-0.2.0.dist-info/METADATA
shiny_tail-0.2.0.dist-info/WHEEL
shiny_tail-0.2.0.dist-info/RECORD
