Metadata-Version: 2.4
Name: shiny_tail
Version: 0.2.0
Summary: A package to use Tailwind CSS in Shiny for Python
Project-URL: Homepage, https://github.com/yourusername/shinytail
Project-URL: Bug Tracker, https://github.com/yourusername/shinytail/issues
Author-email: Daniel Boadzie <boadziedaniel43@gmail.com>
Classifier: License :: OSI Approved :: MIT License
Classifier: Operating System :: OS Independent
Classifier: Programming Language :: Python :: 3
Requires-Python: >=3.7
Requires-Dist: htmltools>=0.6.0
Requires-Dist: shiny>=1.2.1
